{
  "title": "Facit 4420 - Burroughs foto2",
  "description": "Facit 4420, Burroughs. Macchine esposte alla Mostra per il Museo Didattico di Storia dell'Informatica, ottobre-novembre 2021, Padova, Italia.",
  "author": "Piergiovanna Grossi",
  "license": "CC BY-SA 4.0",
  "license_url": "https://creativecommons.org/licenses/by-sa/4.0",
  "source_url": "https://commons.wikimedia.org/wiki/File:Facit_4420_-_Burroughs_foto2.jpg",
  "original_url": "https://upload.wikimedia.org/wikipedia/commons/f/f1/Facit_4420_-_Burroughs_foto2.jpg",
  "attribution_md": "Facit 4420 - Burroughs foto2\nFacit 4420, Burroughs. Macchine esposte alla Mostra per il Museo Didattico di Storia dell'Informatica, ottobre-novembre 2021, Padova, Italia.\n\nImage: Piergiovanna Grossi ([source](https://commons.wikimedia.org/wiki/File:Facit_4420_-_Burroughs_foto2.jpg))\nLicense: [CC BY-SA 4.0](https://creativecommons.org/licenses/by-sa/4.0)"
}
